github_changes/GithubFilteredChanges.py
github_changes/__init__.py
github_changes-1.0.5.dist-info/METADATA
github_changes-1.0.5.dist-info/WHEEL
github_changes-1.0.5.dist-info/top_level.txt
github_changes-1.0.5.dist-info/RECORD
