Metadata-Version: 2.1
Name: github-changes
Version: 1.0.5
Summary: A github file changes module
Home-page: UNKNOWN
Author: danniel
Author-email: danniel.shalev@gmail.com
License: UNKNOWN
Platform: UNKNOWN
Classifier: Programming Language :: Python :: 3
Classifier: License :: OSI Approved :: MIT License
Classifier: Operating System :: OS Independent
Requires-Python: >=3.8
Requires-Dist: Deprecated (==1.2.14)
Requires-Dist: PyGithub (==2.3.0)
Requires-Dist: PyJWT (==2.8.0)
Requires-Dist: PyNaCl (==1.5.0)
Requires-Dist: certifi (==2024.6.2)
Requires-Dist: cffi (==1.16.0)
Requires-Dist: charset-normalizer (==3.3.2)
Requires-Dist: cryptography (==42.0.8)
Requires-Dist: idna (==3.7)
Requires-Dist: pycparser (==2.22)
Requires-Dist: requests (==2.32.3)
Requires-Dist: typing-extensions (==4.12.2)
Requires-Dist: urllib3 (==2.2.2)
Requires-Dist: wrapt (==1.16.0)
